odoo9_addon_account_payment_return-9.0.1.1.0.99.dev2-py2.7-nspkg.pth
odoo9_addon_account_payment_return-9.0.1.1.0.99.dev2.dist-info/METADATA
odoo9_addon_account_payment_return-9.0.1.1.0.99.dev2.dist-info/RECORD
odoo9_addon_account_payment_return-9.0.1.1.0.99.dev2.dist-info/WHEEL
odoo9_addon_account_payment_return-9.0.1.1.0.99.dev2.dist-info/namespace_packages.txt
odoo9_addon_account_payment_return-9.0.1.1.0.99.dev2.dist-info/top_level.txt
odoo_addons/account_payment_return/README.rst
odoo_addons/account_payment_return/__init__.py
odoo_addons/account_payment_return/__openerp__.py
odoo_addons/account_payment_return/data/ir_sequence_data.xml
odoo_addons/account_payment_return/i18n/am.po
odoo_addons/account_payment_return/i18n/ar.po
odoo_addons/account_payment_return/i18n/bg.po
odoo_addons/account_payment_return/i18n/ca.po
odoo_addons/account_payment_return/i18n/cs.po
odoo_addons/account_payment_return/i18n/de.po
odoo_addons/account_payment_return/i18n/el_GR.po
odoo_addons/account_payment_return/i18n/es.po
odoo_addons/account_payment_return/i18n/es_CR.po
odoo_addons/account_payment_return/i18n/es_EC.po
odoo_addons/account_payment_return/i18n/es_ES.po
odoo_addons/account_payment_return/i18n/es_MX.po
odoo_addons/account_payment_return/i18n/es_VE.po
odoo_addons/account_payment_return/i18n/et.po
odoo_addons/account_payment_return/i18n/fi.po
odoo_addons/account_payment_return/i18n/fr.po
odoo_addons/account_payment_return/i18n/gl.po
odoo_addons/account_payment_return/i18n/hr.po
odoo_addons/account_payment_return/i18n/hr_HR.po
odoo_addons/account_payment_return/i18n/it.po
odoo_addons/account_payment_return/i18n/lt.po
odoo_addons/account_payment_return/i18n/nl.po
odoo_addons/account_payment_return/i18n/nl_BE.po
odoo_addons/account_payment_return/i18n/pl.po
odoo_addons/account_payment_return/i18n/pt.po
odoo_addons/account_payment_return/i18n/pt_BR.po
odoo_addons/account_payment_return/i18n/pt_PT.po
odoo_addons/account_payment_return/i18n/ro.po
odoo_addons/account_payment_return/i18n/ru.po
odoo_addons/account_payment_return/i18n/sl.po
odoo_addons/account_payment_return/i18n/th.po
odoo_addons/account_payment_return/i18n/tr.po
odoo_addons/account_payment_return/i18n/vi.po
odoo_addons/account_payment_return/i18n/zh_CN.po
odoo_addons/account_payment_return/models/__init__.py
