Metadata-Version: 2.1
Name: odoo9-addon-account-payment-return
Version: 9.0.1.1.0.99.dev2
Summary: Manage the return of your payments
Home-page: http://www.tecnativa.com
Author: 7 i TRIA, Tecnativa, initOS GmbH & Co., Odoo Community Association (OCA)
Author-email: support@odoo-community.org
License: AGPL-3
Platform: UNKNOWN
Classifier: Programming Language :: Python
Classifier: Framework :: Odoo
Classifier: License :: OSI Approved :: GNU Affero General Public License v3
Requires-Python: ~=2.7
Requires-Dist: odoo (<9.1a,>=9.0a)
